bmf/__init__.py
bmf-0.0.1.dist-info/METADATA
bmf-0.0.1.dist-info/WHEEL
bmf-0.0.1.dist-info/top_level.txt
bmf-0.0.1.dist-info/RECORD
