Metadata-Version: 2.1
Name: bmf
Version: 0.0.1
Summary: Library to query german tax provider bmf
Home-page: https://github.com/crs/bmf
Author: Christian Spaniol
Author-email: christian.spaniol@cpro-iot.com
Classifier: Programming Language :: Python :: 3
Classifier: License :: OSI Approved :: MIT License
Classifier: Operating System :: OS Independent
Requires-Python: >=3.10
Requires-Dist: requests
